simo_sonos/__init__.py
simo_sonos/admin.py
simo_sonos/controllers.py
simo_sonos/forms.py
simo_sonos/gateways.py
simo_sonos/models.py
simo_sonos/utils.py
simo_sonos/__pycache__/__init__.cpython-38.pyc
simo_sonos/__pycache__/admin.cpython-38.pyc
simo_sonos/__pycache__/controllers.cpython-38.pyc
simo_sonos/__pycache__/forms.cpython-38.pyc
simo_sonos/__pycache__/gateways.cpython-38.pyc
simo_sonos/__pycache__/models.cpython-38.pyc
simo_sonos/__pycache__/utils.cpython-38.pyc
simo_sonos/migrations/0001_initial.py
simo_sonos/migrations/0002_rename_master_sonosplayer_slave_of.py
simo_sonos/migrations/0003_alter_sonosplaylist_item_id.py
simo_sonos/migrations/__init__.py
simo_sonos/migrations/__pycache__/0001_initial.cpython-38.pyc
simo_sonos/migrations/__pycache__/0002_rename_master_sonosplayer_slave_of.cpython-38.pyc
simo_sonos/migrations/__pycache__/0003_alter_sonosplaylist_item_id.cpython-38.pyc
simo_sonos/migrations/__pycache__/__init__.cpython-38.pyc
simo_sonos-1.2.15.dist-info/LICENSE.md
simo_sonos-1.2.15.dist-info/METADATA
simo_sonos-1.2.15.dist-info/WHEEL
simo_sonos-1.2.15.dist-info/top_level.txt
simo_sonos-1.2.15.dist-info/RECORD
