Metadata-Version: 2.2
Name: simo-sonos
Version: 1.2.15
Summary: SONOS integration for SIMO.io
Author-email: Simanas Venčkauskas <simanas@simo.io>
Project-URL: Homepage, https://github.com/SIMO-io/simo-sonos
Project-URL: Issues, https://github.com/SIMO-io/simo-sonos/issues
Classifier: Programming Language :: Python :: 3
Classifier: License :: OSI Approved :: MIT License
Classifier: Operating System :: OS Independent
Requires-Python: >=3.8
License-File: LICENSE.md
Requires-Dist: simo>=1.5.9
Requires-Dist: soco==0.29.1
